{"SubTexture":[{"width":25,"y":1,"height":28,"name":"Right_leg03","x":223},{"width":16,"y":261,"height":18,"name":"Right_leg","x":1},{"width":24,"y":86,"height":21,"name":"Right_leg02","x":223},{"width":17,"y":137,"height":26,"name":"right_arm","x":223},{"width":42,"y":243,"height":16,"name":"right_arm04","x":1},{"width":39,"y":261,"height":18,"name":"right_arm03","x":207},{"y":61,"frameX":-1,"frameY":0,"width":30,"frameWidth":30,"height":23,"name":"right_arm02","frameHeight":23,"x":223},{"width":29,"y":210,"height":19,"name":"left_leg02","x":68},{"width":25,"y":31,"height":28,"name":"left_leg03","x":223},{"width":16,"y":261,"height":18,"name":"left_leg","x":19},{"width":117,"y":1,"height":96,"name":"ears","x":1},{"width":65,"y":186,"height":55,"name":"ears02","x":1},{"width":40,"y":237,"height":22,"name":"body02","x":207},{"width":38,"y":206,"height":29,"name":"body03","x":207},{"width":39,"y":175,"height":29,"name":"body","x":207},{"y":243,"frameX":0,"frameY":0,"width":42,"frameWidth":42,"height":16,"name":"left_arm04","frameHeight":16,"x":45},{"width":17,"y":109,"height":26,"name":"left_arm","x":223},{"y":186,"frameX":0,"frameY":0,"width":30,"frameWidth":30,"height":22,"name":"left_arm02","frameHeight":23,"x":68},{"width":101,"y":175,"height":85,"name":"head03","x":104},{"width":101,"y":1,"height":85,"name":"head04","x":120},{"width":101,"y":88,"height":85,"name":"head02","x":120},{"width":101,"y":99,"height":85,"name":"head","x":1}],"width":256,"height":512,"name":"anais","imagePath":"anais_tex.png"}